<?xml version="1.0" encoding="utf-8" ?>
<dwsync>
<file name="bg1.jpg" server="G:/cxl/work/Uzg/Uzg-web/" local="130864568565608364" remote="130864568560000000" Dst="0" />
<file name="quan_bg.png" server="G:/cxl/work/Uzg/Uzg-web/" local="130864573600506343" remote="130864573600000000" Dst="0" />
<file name="quan_bg2.png" server="G:/cxl/work/Uzg/Uzg-web/" local="130865457277906403" remote="130865457270000000" Dst="0" />
<file name="close_btn.png" server="G:/cxl/work/Uzg/Uzg-web/" local="130864624227982069" remote="130864624220000000" Dst="0" />
<file name="top_pic.jpg" server="G:/cxl/work/Uzg/Uzg-web/" local="130864567712279556" remote="130864567710000000" Dst="0" />
<file name="txt1.png" server="G:/cxl/work/Uzg/Uzg-web/" local="130864570886211094" remote="130864570880000000" Dst="0" />
<file name="xinfeng.png" server="G:/cxl/work/Uzg/Uzg-web/" local="130864573600876364" remote="130864573600000000" Dst="0" />
<file name="logo.png" server="G:/cxl/work/Uzg/Uzg-web/" local="130864630749745093" remote="130864630740000000" Dst="0" />
</dwsync>